{
  "project_info": {
    "project_number": "606298400178",
    "firebase_url": "https://my-databases-dad68.firebaseio.com",
    "project_id": "my-databases-dad68",
    "storage_bucket": "my-databases-dad68.appspot.com"
  },
  "client": [
    {
      "client_info": {
        "mobilesdk_app_id": "1:606298400178:android:6ad2db9796d04c61",
        "android_client_info": {
          "package_name": "com.kolo.him.himdatabase"
        }
      },
      "oauth_client": [
        {
          "client_id": "606298400178-qdbkpk6kpn9mp2drsoitrsgoscmb74ju.apps.googleusercontent.com",
          "client_type": 3
        }
      ],
      "api_key": [
        {
          "current_key": "AIzaSyDpiWN1rVu3CMMe87M1rmADqLL_zAzMEc0"
        }
      ],
      "services": {
        "analytics_service": {
          "status": 1
        },
        "appinvite_service": {
          "status": 1,
          "other_platform_oauth_client": []
        },
        "ads_service": {
          "status": 2
        }
      }
    },
    {
      "client_info": {
        "mobilesdk_app_id": "1:606298400178:android:0da4fda23feb62bc",
        "android_client_info": {
          "package_name": "com.koloapps.contest.cryptocomparecurrencyconverter"
        }
      },
      "oauth_client": [
        {
          "client_id": "606298400178-qdbkpk6kpn9mp2drsoitrsgoscmb74ju.apps.googleusercontent.com",
          "client_type": 3
        }
      ],
      "api_key": [
        {
          "current_key": "AIzaSyDpiWN1rVu3CMMe87M1rmADqLL_zAzMEc0"
        }
      ],
      "services": {
        "analytics_service": {
          "status": 1
        },
        "appinvite_service": {
          "status": 1,
          "other_platform_oauth_client": []
        },
        "ads_service": {
          "status": 2
        }
      },
      "admob_app_id": "ca-app-pub-3517746418699749~7280583326"
    },
    {
      "client_info": {
        "mobilesdk_app_id": "1:606298400178:android:74763c941906aebd",
        "android_client_info": {
          "package_name": "com.koloapps.cryptocompareconverter"
        }
      },
      "oauth_client": [
        {
          "client_id": "606298400178-qdbkpk6kpn9mp2drsoitrsgoscmb74ju.apps.googleusercontent.com",
          "client_type": 3
        }
      ],
      "api_key": [
        {
          "current_key": "AIzaSyDpiWN1rVu3CMMe87M1rmADqLL_zAzMEc0"
        }
      ],
      "services": {
        "analytics_service": {
          "status": 1
        },
        "appinvite_service": {
          "status": 1,
          "other_platform_oauth_client": []
        },
        "ads_service": {
          "status": 2
        }
      }
    },
    {
      "client_info": {
        "mobilesdk_app_id": "1:606298400178:android:756590e171102a45",
        "android_client_info": {
          "package_name": "com.koloapps.himquickguide"
        }
      },
      "oauth_client": [
        {
          "client_id": "606298400178-qdbkpk6kpn9mp2drsoitrsgoscmb74ju.apps.googleusercontent.com",
          "client_type": 3
        }
      ],
      "api_key": [
        {
          "current_key": "AIzaSyDpiWN1rVu3CMMe87M1rmADqLL_zAzMEc0"
        }
      ],
      "services": {
        "analytics_service": {
          "status": 1
        },
        "appinvite_service": {
          "status": 1,
          "other_platform_oauth_client": []
        },
        "ads_service": {
          "status": 2
        }
      }
    }
  ],
  "configuration_version": "1"
}